setup.py
Topsis_Soumil_101903663.egg-info/PKG-INFO
Topsis_Soumil_101903663.egg-info/SOURCES.txt
Topsis_Soumil_101903663.egg-info/dependency_links.txt
Topsis_Soumil_101903663.egg-info/requires.txt
Topsis_Soumil_101903663.egg-info/top_level.txt
topsis/topsis-101903663.py