Metadata-Version: 2.1
Name: Topsis-Soumil-101903663
Version: 0.0.1
Summary: A Python package to find TOPSIS for multi-criteria decision analysis method
Home-page: https://github.com/maitra100/topsis/archive/refs/tags/0.0.1.tar.gz
Author: Soumil Maitra
Author-email: smaitra_be19@thapar.edu
License: MIT
Keywords: Topsis,UCS654,101903663
Platform: UNKNOWN
Classifier: Development Status :: 3 - Alpha
Classifier: Intended Audience :: Developers
Classifier: Operating System :: Microsoft :: Windows :: Windows 10
Classifier: License :: OSI Approved :: MIT License
Classifier: Programming Language :: Python :: 3
